setup.py
django_zqiniu/__init__.py
django_zqiniu/fields.py
django_zqiniu/file.py
django_zqiniu/storage.py
django_zqiniu.egg-info/PKG-INFO
django_zqiniu.egg-info/SOURCES.txt
django_zqiniu.egg-info/dependency_links.txt
django_zqiniu.egg-info/requires.txt
django_zqiniu.egg-info/top_level.txt