Metadata-Version: 1.1
Name: django-zqiniu
Version: 0.3
Summary: 在Django中集成七牛服务
Home-page: https://github.com/hunter007/django-zqiniu
Author: hunter007
Author-email: wentao79@gmail.com
License: MIT
Platform: any
Classifier: Intended Audience :: Developers
Classifier: License :: OSI Approved :: MIT License
Classifier: Operating System :: OS Independent
Classifier: Programming Language :: Python
Classifier: Programming Language :: Python :: 2
Classifier: Programming Language :: Python :: 2.6
Classifier: Programming Language :: Python :: 2.7
Classifier: Topic :: Internet :: WWW/HTTP :: Dynamic Content
Classifier: Topic :: Software Development :: Libraries :: Python Modules
